nonebot_plugin_moellmchats/Categorize.py
nonebot_plugin_moellmchats/Config.py
nonebot_plugin_moellmchats/MessagesHandler.py
nonebot_plugin_moellmchats/ModelSelector.py
nonebot_plugin_moellmchats/Search.py
nonebot_plugin_moellmchats/TemperamentManager.py
nonebot_plugin_moellmchats/__init__.py
nonebot_plugin_moellmchats/moe_llm.py
nonebot_plugin_moellmchats/utils.py
nonebot_plugin_moellmchats-0.15.11.dist-info/LICENSE
nonebot_plugin_moellmchats-0.15.11.dist-info/METADATA
nonebot_plugin_moellmchats-0.15.11.dist-info/WHEEL
nonebot_plugin_moellmchats-0.15.11.dist-info/RECORD
