Metadata-Version: 2.3
Name: nonebot-plugin-moellmchats
Version: 0.15.11
Summary: A Nonebot plugin, Multi-Model Chat System | Hybrid Scheduling·Search Augmented·Persona Customization
License: GPL
Keywords: nonebot,nonebot2,llm,ai,chat
Author: Elflare
Requires-Python: >=3.9,<4.0
Classifier: License :: Other/Proprietary License
Classifier: Programming Language :: Python :: 3
Classifier: Programming Language :: Python :: 3.9
Classifier: Programming Language :: Python :: 3.10
Classifier: Programming Language :: Python :: 3.11
Classifier: Programming Language :: Python :: 3.12
Classifier: Programming Language :: Python :: 3.13
Requires-Dist: aiohttp (>=3.8.1,<4.0.0)
Requires-Dist: nonebot-adapter-onebot (>=2.0.0,<3.0.0)
Requires-Dist: nonebot-plugin-localstore (>=0.7.0,<0.8.0)
Requires-Dist: nonebot2 (>=2.2.0,<3.0.0)
Requires-Dist: ujson (>=5.7.0,<6.0.0)
Project-URL: Documentation, https://github.com/Elflare/nonebot-plugin-moellmchats#readme
Project-URL: Homepage, https://github.com/Elflare/nonebot-plugin-moellmchats
Project-URL: Repository, https://github.com/Elflare/nonebot-plugin-moellmchats
